ueq/__init__.py
ueq/core.py
ueq/methods/__init__.py
ueq/methods/bayesian_linear.py
ueq/methods/bootstrap.py
ueq/methods/conformal.py
ueq/methods/cross_ensemble.py
ueq/methods/deep_ensemble.py
ueq/methods/mc_dropout.py
ueq/utils/__init__.py
ueq/utils/api.py
ueq/utils/metrics.py
ueq/utils/monitoring.py
ueq/utils/performance.py
ueq/utils/plotting.py
ueq/utils/visualization.py
ueq-1.0.1.dist-info/LICENSE
ueq-1.0.1.dist-info/METADATA
ueq-1.0.1.dist-info/WHEEL
ueq-1.0.1.dist-info/top_level.txt
ueq-1.0.1.dist-info/RECORD
