Metadata-Version: 2.1
Name: ueq
Version: 1.0.1
Summary: Uncertainty Everywhere (UEQ) - Phoenix Edition: A unified Python library for Uncertainty Quantification with production-ready features
Author: Kiplangat Korir
Author-email: korirkiplangat22@gmail.com
License: Apache-2.0
Project-URL: Source, https://github.com/kiplangatkorir/ueq
Project-URL: Bug Reports, https://github.com/kiplangatkorir/ueq/issues
Keywords: uncertainty-quantification,machine-learning,deep-learning,bootstrap,conformal-prediction,mc-dropout,production,monitoring,auto-detection,cross-framework,phoenix
Classifier: Development Status :: 4 - Beta
Classifier: Intended Audience :: Science/Research
Classifier: Intended Audience :: Developers
Classifier: Programming Language :: Python :: 3.8
Classifier: Programming Language :: Python :: 3.9
Classifier: Programming Language :: Python :: 3.10
Classifier: Programming Language :: Python :: 3.11
Classifier: Programming Language :: Python :: 3.12
Classifier: Topic :: Scientific/Engineering :: Artificial Intelligence
Classifier: Topic :: Software Development :: Libraries :: Python Modules
Classifier: Topic :: Scientific/Engineering :: Information Analysis
Requires-Python: >=3.8
License-File: LICENSE
Requires-Dist: numpy>=1.19.0
Requires-Dist: scipy>=1.7.0
Requires-Dist: scikit-learn>=0.24.0
Requires-Dist: torch>=1.9.0
Requires-Dist: pandas>=1.3.0
Requires-Dist: matplotlib>=3.4.0
Provides-Extra: dev
Requires-Dist: pytest>=6.0.0; extra == "dev"
Requires-Dist: black>=21.0.0; extra == "dev"
Requires-Dist: pylint>=2.8.0; extra == "dev"
